AUTHORS.rst
CONTRIBUTING.rst
HISTORY.rst
LICENSE
MANIFEST.in
README.rst
setup.cfg
setup.py
docs/Makefile
docs/authors.rst
docs/conf.py
docs/contributing.rst
docs/history.rst
docs/index.rst
docs/installation.rst
docs/make.bat
docs/readme.rst
docs/usage.rst
fppv/__init__.py
fppv/cli.py
fppv/fppv.py
fppv/version.py
fppv.egg-info/PKG-INFO
fppv.egg-info/SOURCES.txt
fppv.egg-info/dependency_links.txt
fppv.egg-info/entry_points.txt
fppv.egg-info/not-zip-safe
fppv.egg-info/top_level.txt
tests/__init__.py
tests/test_fppv.py