Metadata-Version: 1.1
Name: fppv
Version: 0.1.1
Summary: Find Python Package Version
Home-page: https://github.com/kdheepak89/fppv
Author: Dheepak Krishnamurthy
Author-email: kdheepak89@gmail.com
License: ISCL
Keywords: fppv
Platform: UNKNOWN
Classifier: Development Status :: 2 - Pre-Alpha
Classifier: Intended Audience :: Developers
Classifier: License :: OSI Approved :: ISC License (ISCL)
Classifier: Natural Language :: English
Classifier: Programming Language :: Python :: 2
Classifier: Programming Language :: Python :: 2.6
Classifier: Programming Language :: Python :: 2.7
Classifier: Programming Language :: Python :: 3
Classifier: Programming Language :: Python :: 3.3
Classifier: Programming Language :: Python :: 3.4
Classifier: Programming Language :: Python :: 3.5
